hoyolab_rss_feeds-2.5.0.dist-info/licenses/LICENSE
hoyolabrssfeeds/__init__.py
hoyolabrssfeeds/__main__.py
hoyolabrssfeeds/configs.py
hoyolabrssfeeds/errors.py
hoyolabrssfeeds/feeds.py
hoyolabrssfeeds/hoyolab.py
hoyolabrssfeeds/loaders.py
hoyolabrssfeeds/models.py
hoyolabrssfeeds/py.typed
hoyolabrssfeeds/writers.py
hoyolab_rss_feeds-2.5.0.dist-info/METADATA
hoyolab_rss_feeds-2.5.0.dist-info/WHEEL
hoyolab_rss_feeds-2.5.0.dist-info/entry_points.txt
hoyolab_rss_feeds-2.5.0.dist-info/top_level.txt
hoyolab_rss_feeds-2.5.0.dist-info/RECORD
