Metadata-Version: 2.4
Name: hoyolab-rss-feeds
Version: 2.5.0
Summary: RSS feed generator for official game news from Hoyolab.
Author: c3kay
License: MIT License
Project-URL: Repository, https://github.com/c3kay/hoyolab-rss-feeds
Project-URL: Homepage, https://c3kay.de/hoyolab-rss-feeds
Keywords: hoyolab,rss,feed,rss-generator,jsonfeed,atom,genshin-impact,honkai-impact,zenless-zone-zero
Classifier: Programming Language :: Python :: 3
Classifier: Programming Language :: Python :: 3.10
Classifier: Programming Language :: Python :: 3.11
Classifier: Programming Language :: Python :: 3.12
Classifier: Programming Language :: Python :: 3.13
Classifier: License :: OSI Approved :: MIT License
Classifier: Operating System :: OS Independent
Classifier: Development Status :: 5 - Production/Stable
Classifier: Intended Audience :: Developers
Classifier: Intended Audience :: System Administrators
Classifier: Topic :: Internet :: WWW/HTTP :: Dynamic Content :: News/Diary
Requires-Python: >=3.10
License-File: LICENSE
Requires-Dist: aiohttp~=3.11.18
Requires-Dist: aiofiles~=24.1.0
Requires-Dist: pydantic<2,~=1.10.0
Requires-Dist: tomli~=2.2.1; python_version < "3.11"
Provides-Extra: dev
Requires-Dist: tox~=4.26.0; extra == "dev"
Requires-Dist: pytest~=8.3.5; extra == "dev"
Requires-Dist: pytest-asyncio~=0.24.0; extra == "dev"
Requires-Dist: pytest-cov~=6.1.1; extra == "dev"
Requires-Dist: pytest-mock~=3.14.0; extra == "dev"
Requires-Dist: atoma~=0.0.17; extra == "dev"
Requires-Dist: langdetect~=1.0.9; extra == "dev"
Dynamic: license-file
